Metadata-Version: 2.1
Name: pgElephant
Version: 1.0.5
Summary: PostgreSQL Database Manager
Author: Ryan Souza Anselmo
Author-email: ryansouza.cwb@gmail.com
License: MIT License
Keywords: pgElephant
License-File: LICENSE
